README.md
setup.py
fortnite.egg-info/PKG-INFO
fortnite.egg-info/SOURCES.txt
fortnite.egg-info/dependency_links.txt
fortnite.egg-info/requires.txt
fortnite.egg-info/top_level.txt
pfaw/__init__.py
pfaw/constants.py
pfaw/core.py
pfaw/objects.py
pfaw/utils.py