Metadata-Version: 2.1
Name: fortnite
Version: 0.0.8
Summary: The Python Fortnite API Wrapper
Home-page: https://github.com/nicolaskenner/python-fortnite-api-wrapper
Author: Nicolas Kenner
Author-email: nick@nicolaskenner.com
License: UNKNOWN
Platform: UNKNOWN
Classifier: Development Status :: 3 - Alpha
Classifier: Intended Audience :: Developers
Classifier: License :: OSI Approved :: MIT License
Classifier: Programming Language :: Python :: 3
